Metadata-Version: 2.1
Name: odoo-addon-l10n_co_currency_rate_update
Version: 18.0.1.0.0.2
Requires-Python: >=3.10
Requires-Dist: odoo-addon-currency_rate_update==18.0.*
Requires-Dist: odoo==18.0.*
Summary: Tasa de cambio de Superfinanciera para Colombia
Home-page: https://github.com/OCA/l10n-colombia
License: AGPL-3
Author: Yan Chirino, Odoo Community Association (OCA)
Author-email: support@odoo-community.org
Classifier: Programming Language :: Python
Classifier: Framework :: Odoo
Classifier: Framework :: Odoo :: 18.0
Classifier: License :: OSI Approved :: GNU Affero General Public License v3
